spladtool/__init__.py
spladtool/spladtool_forward.py
spladtool/spladtool_reverse.py
spladtool/utils.py
spladtool-0.0.5.dist-info/LICENSE
spladtool-0.0.5.dist-info/METADATA
spladtool-0.0.5.dist-info/WHEEL
spladtool-0.0.5.dist-info/top_level.txt
spladtool-0.0.5.dist-info/RECORD
