Metadata-Version: 2.1
Name: spladtool
Version: 0.0.5
Summary: The Simple Pytorch-Like Auto Differentiation Toolkit is an automatic differentiation package for calculating gradients of a function in forward and reverse mode.
Home-page: https://github.com/cs107-rysr/cs107-FinalProject
Author: Raymond Jow, Rye Julson, Shihan Lin, Yuanbiao Wang
Author-email: rjow@college.harvard.edu
License: MIT
Project-URL: Documentation, https://spladtool-docs.readthedocs.io/en/latest/index.html
Platform: UNKNOWN
Classifier: Programming Language :: Python :: 3
Classifier: License :: OSI Approved :: MIT License
Classifier: Operating System :: OS Independent
Requires-Python: >=3.7
Requires-Dist: numpy
